odootools_docker/__init__.py
odootools_docker/renderer.py
odootools_docker/tools.py
odootools_docker/cli/__init__.py
odootools_docker/cli/build.py
odootools_docker/cli/context.py
odootools_docker/cli/docker.py
odootools_docker/cli/platform.py
odootools_docker/cli/wkhtmltopdf.py
odootools_docker/templates/header.jinja
odootools_docker/templates/main.jinja
odootools_docker/templates/prepare_user.jinja
odootools_docker/templates/setup_base_dependencies.jinja
odootools_docker/templates/setup_command.jinja
odootools_docker/templates/setup_env.jinja
odootools_docker/templates/setup_labels.jinja
odootools_docker/templates/setup_odoo.jinja
odootools_docker-0.1.0.dist-info/METADATA
odootools_docker-0.1.0.dist-info/WHEEL
odootools_docker-0.1.0.dist-info/entry_points.txt
odootools_docker-0.1.0.dist-info/top_level.txt
odootools_docker-0.1.0.dist-info/RECORD
