Metadata-Version: 2.1
Name: odootools-docker
Version: 0.1.0
Summary: Odootools script to generate docker images
Home-page: https://github.com/odoo-plus/odootools-docker
Author: Loïc Faure-Lacroix
Author-email: lamerstar@gmail.com
Project-URL: Bug Tracker, https://github.com/odoo-plus/odootools-docker/issues
Classifier: Programming Language :: Python :: 3
Classifier: License :: OSI Approved :: MIT License
Classifier: Operating System :: OS Independent
Requires-Python: >=3.6
Requires-Dist: Jinja2
Requires-Dist: click
